peerjs_py/__init__.py
peerjs_py/__main__.py
peerjs_py/api.py
peerjs_py/base_connection.py
peerjs_py/encodingQueue.py
peerjs_py/enums.py
peerjs_py/logger.py
peerjs_py/mediaconnection.py
peerjs_py/msgPackPeer.py
peerjs_py/negotiator.py
peerjs_py/option_interfaces.py
peerjs_py/peer.py
peerjs_py/peer_error.py
peerjs_py/servermessage.py
peerjs_py/socket.py
peerjs_py/supports.py
peerjs_py/util.py
peerjs_py/binarypack/binarypack.py
peerjs_py/binarypack/bufferbuilder.py
peerjs_py/dataconnection/DataConnection.py
peerjs_py/dataconnection/__init__.py
peerjs_py/dataconnection/BufferedConnection/BinaryPack.py
peerjs_py/dataconnection/BufferedConnection/BufferedConnection.py
peerjs_py/dataconnection/BufferedConnection/Json.py
peerjs_py/dataconnection/BufferedConnection/Raw.py
peerjs_py/dataconnection/BufferedConnection/__init__.py
peerjs_py/dataconnection/BufferedConnection/binaryPackChunker.py
peerjs_py/dataconnection/StreamConnection/MsgPack.py
peerjs_py/dataconnection/StreamConnection/StreamConnection.py
peerjs_py/dataconnection/StreamConnection/__init__.py
peerjs_py/utils/__init__.py
peerjs_py/utils/random_token.py
peerjs_py/utils/validateId.py
peerjs_py-0.1.1.dist-info/METADATA
peerjs_py-0.1.1.dist-info/WHEEL
peerjs_py-0.1.1.dist-info/top_level.txt
peerjs_py-0.1.1.dist-info/RECORD
