Metadata-Version: 2.1
Name: peerjs_py
Version: 0.1.1
Summary: A Python implementation of PeerJS
Home-page: https://github.com/sellpath/peerjs_py
Author: Mansu Kim
Author-email: Mansu Kim <mkim@sellpath.com>
Keywords: peerjs,webrtc,networking
Classifier: License :: OSI Approved :: MIT License
Classifier: Programming Language :: Python
Classifier: Programming Language :: Python :: 3
Requires-Python: >=3.6
Requires-Dist: aiortc<2.0.0,>=1.9.0
Requires-Dist: pyee<13.0.0,>=12.0.0
Requires-Dist: aiohttp<4.0.0,>=3.7.4
Requires-Dist: requests<3.0.0,>=2.25.1
Provides-Extra: test
Requires-Dist: pytest; extra == "test"
Requires-Dist: python-socketio; extra == "test"
Requires-Dist: soundfile; extra == "test"
Requires-Dist: numpy; extra == "test"
Requires-Dist: pydub; extra == "test"
Requires-Dist: scipy; extra == "test"
